roboto/__init__.py
roboto/api_types.py
roboto/bot.py
roboto/datautil.py
roboto/error.py
roboto/http_api.py
roboto/media.py
roboto/py.typed
roboto/request_types.py
roboto/typing_util.py
roboto/url.py
roboto_telegram-0.4.0.dist-info/LICENSE.md
roboto_telegram-0.4.0.dist-info/WHEEL
roboto_telegram-0.4.0.dist-info/METADATA
roboto_telegram-0.4.0.dist-info/RECORD
