Metadata-Version: 2.1
Name: roboto-telegram
Version: 0.4.0
Summary: A type-hinted async Telegram bot library.
License: MIT
Author: Tarcísio Eduardo Moreira Crocomo
Author-email: tarcisioe@pm.me
Requires-Python: >=3.7,<4.0
Classifier: License :: OSI Approved :: MIT License
Classifier: Programming Language :: Python :: 3
Classifier: Programming Language :: Python :: 3.7
Classifier: Programming Language :: Python :: 3.8
Requires-Dist: asks (>=2.4.7,<3.0.0)
Requires-Dist: typing-extensions (>=3.7.4,<4.0.0)
Requires-Dist: typing-inspect (>=0.6.0,<0.7.0)
Requires-Dist: validators (>=0.15.0,<0.16.0)
